{"meta":{"id":"ustv-b25e9331-bc95-4e31-afaf-54301ff1d1dd","tvgId":"","name":"Disney XD","country":"USA","countryCode":"us","genre":"Kids","logo":"https://raw.githubusercontent.com/yowmamasita/usa-tv-next/main/public/logos/usa/disney-xd-us.png","time":null,"type":"tv","poster":"https://raw.githubusercontent.com/yowmamasita/usa-tv-next/main/public/posters/usa/disney-xd-us.png","genres":["Kids"],"streams":[{"url":"https://fl7.moveonjoy.com/DISNEY_XD/index.m3u8","behaviorHints":{"notWebReady":true},"name":"[DEAD] HD","description":"MJ"},{"url":"http://23.237.104.106:8080/USA_DISNEY_XD/index.m3u8","behaviorHints":{"notWebReady":true},"name":"HD","description":"MJE"},{"url":"https://tvpass.org/live/DisneyXDEast/sd","behaviorHints":{"notWebReady":true},"name":"SD","description":"TP"}]}}